MANIFEST.in
README.rst
requirements.txt
setup.cfg
setup.py
djmicrosip_cambiaprecios/__init__.py
djmicrosip_cambiaprecios/__init__.pyc
djmicrosip_cambiaprecios/config.pyc
djmicrosip_cambiaprecios/forms.pyc
djmicrosip_cambiaprecios/models.pyc
djmicrosip_cambiaprecios/urls.pyc
djmicrosip_cambiaprecios/views.pyc
djmicrosip_cambiaprecios.egg-info/PKG-INFO
djmicrosip_cambiaprecios.egg-info/SOURCES.txt
djmicrosip_cambiaprecios.egg-info/dependency_links.txt
djmicrosip_cambiaprecios.egg-info/requires.txt
djmicrosip_cambiaprecios.egg-info/top_level.txt
djmicrosip_cambiaprecios/modulos/__init__.py
djmicrosip_cambiaprecios/modulos/__init__.pyc
djmicrosip_cambiaprecios/modulos/herramientas/__init__.py
djmicrosip_cambiaprecios/modulos/herramientas/__init__.pyc
djmicrosip_cambiaprecios/modulos/herramientas/forms.pyc
djmicrosip_cambiaprecios/modulos/herramientas/models.pyc
djmicrosip_cambiaprecios/modulos/herramientas/urls.pyc
djmicrosip_cambiaprecios/modulos/herramientas/views.pyc
djmicrosip_cambiaprecios/static/js/djmicrosip_cambiaprecios/buscar_articulo.js
djmicrosip_cambiaprecios/static/js/djmicrosip_cambiaprecios/cambia_precios.js
djmicrosip_cambiaprecios/templates/djmicrosip_cambiaprecios/articulo.html
djmicrosip_cambiaprecios/templates/djmicrosip_cambiaprecios/articulo_mobile.html
djmicrosip_cambiaprecios/templates/djmicrosip_cambiaprecios/articulos.html
djmicrosip_cambiaprecios/templates/djmicrosip_cambiaprecios/base.html
djmicrosip_cambiaprecios/templates/djmicrosip_cambiaprecios/index.html
djmicrosip_cambiaprecios/templates/djmicrosip_cambiaprecios/herramientas/preferencias.html